awaitedreqs/__init__.py
awaitedreqs-0.1.1.dist-info/METADATA
awaitedreqs-0.1.1.dist-info/WHEEL
awaitedreqs-0.1.1.dist-info/top_level.txt
awaitedreqs-0.1.1.dist-info/RECORD
