Metadata-Version: 2.4
Name: awaitedreqs
Version: 0.1.1
Summary: Async requests-like HTTP client built on aiohttp with requests-compatible API
Home-page: https://github.com/kokofixcomputers/awaitedreqs
Author: kokodev
Author-email: koko@kokodev.cc
Keywords: async http requests aiohttp http-client
Classifier: Programming Language :: Python :: 3
Classifier: Programming Language :: Python :: 3.7
Classifier: Programming Language :: Python :: 3.8
Classifier: Programming Language :: Python :: 3.9
Classifier: Programming Language :: Python :: 3.10
Classifier: Operating System :: OS Independent
Classifier: License :: OSI Approved :: MIT License
Classifier: Intended Audience :: Developers
Classifier: Topic :: Internet :: WWW/HTTP :: HTTP Servers
Requires-Python: >=3.7
Requires-Dist: aiohttp>=3.8.0
Requires-Dist: chardet
Dynamic: author
Dynamic: author-email
Dynamic: classifier
Dynamic: description
Dynamic: description-content-type
Dynamic: home-page
Dynamic: keywords
Dynamic: requires-dist
Dynamic: requires-python
Dynamic: summary
